linkedlist/__init__.py
linkedlist/linkedlist.py
py_linkedlist-0.0.12.dist-info/METADATA
py_linkedlist-0.0.12.dist-info/WHEEL
py_linkedlist-0.0.12.dist-info/top_level.txt
py_linkedlist-0.0.12.dist-info/RECORD
