Metadata-Version: 2.1
Name: py-linkedlist
Version: 0.0.12
Summary: LinkedList Package
Home-page: UNKNOWN
Author: Rajesh Kumar Patnala
Author-email: patnala04@gmail.com
License: UNKNOWN
Keywords: python,dsa,data structures,linkedlist,linked list,algorithms
Platform: UNKNOWN
Classifier: Development Status :: 1 - Planning
Classifier: Intended Audience :: Developers
Classifier: Intended Audience :: Education
Classifier: Intended Audience :: End Users/Desktop
Classifier: Programming Language :: Python :: 3
Classifier: Programming Language :: Python :: 3.8
Classifier: Operating System :: Unix
Classifier: Operating System :: MacOS :: MacOS X
Classifier: Operating System :: Microsoft :: Windows
